{
  "kind": "collectionType",
  "collectionName": "location_trackings",
  "info": {
    "singularName": "location-tracking",
    "pluralName": "location-trackings",
    "displayName": "Location Tracking",
    "description": ""
  },
  "options": {
    "draftAndPublish": true
  },
  "pluginOptions": {},
  "attributes": {
    "label": {
      "type": "string"
    },
    "latitude": {
      "type": "float"
    },
    "longitude": {
      "type": "float"
    },
    "last_verified": {
      "type": "datetime"
    },
    "plant": {
      "type": "relation",
      "relation": "oneToOne",
      "target": "api::plant.plant"
    },
    "user": {
      "type": "relation",
      "relation": "oneToOne",
      "target": "plugin::users-permissions.user"
    },
    "plant_image": {
      "type": "media",
      "multiple": false,
      "required": false,
      "allowedTypes": [
        "images",
        "files",
        "videos",
        "audios"
      ]
    },
    "analysis": {
      "type": "text"
    },
    "planted_date": {
      "type": "date"
    },
    "is_plant": {
      "type": "boolean"
    },
    "confidence": {
      "type": "enumeration",
      "enum": [
        "high",
        "medium",
        "low",
        "unknown",
        "unverified"
      ]
    },
    "map_layer": {
      "type": "enumeration",
      "enum": [
        "fruit_tree",
        "pollinator",
        "garden",
        "other"
      ]
    },
    "location_image": {
      "allowedTypes": [
        "images",
        "files",
        "videos",
        "audios"
      ],
      "type": "media",
      "multiple": false
    },
    "garden": {
      "type": "relation",
      "relation": "manyToOne",
      "target": "api::garden.garden",
      "inversedBy": "location_trackings"
    },
    "garden_assignment_status": {
      "type": "enumeration",
      "enum": [
        "unassigned",
        "pending_confirmation",
        "confirmed",
        "declined"
      ],
      "default": "unassigned"
    },
    "suggested_distance_meters": {
      "type": "float"
    },
    "suggested_match_method": {
      "type": "enumeration",
      "enum": [
        "inside_polygon",
        "within_radius"
      ]
    }
  }
}
