{"id":1,"name":"buckets.jpg","alternativeText":null,"caption":null,"width":800,"height":1067,"formats":{"large":{"ext":".jpg","url":"/uploads/large_buckets_07cf4a875d.jpg","hash":"large_buckets_07cf4a875d","mime":"image/jpeg","name":"large_buckets.jpg","path":null,"size":205.84,"width":750,"height":1000},"small":{"ext":".jpg","url":"/uploads/small_buckets_07cf4a875d.jpg","hash":"small_buckets_07cf4a875d","mime":"image/jpeg","name":"small_buckets.jpg","path":null,"size":64.36,"width":375,"height":500},"medium":{"ext":".jpg","url":"/uploads/medium_buckets_07cf4a875d.jpg","hash":"medium_buckets_07cf4a875d","mime":"image/jpeg","name":"medium_buckets.jpg","path":null,"size":129.31,"width":562,"height":750},"thumbnail":{"ext":".jpg","url":"/uploads/thumbnail_buckets_07cf4a875d.jpg","hash":"thumbnail_buckets_07cf4a875d","mime":"image/jpeg","name":"thumbnail_buckets.jpg","path":null,"size":7.95,"width":117,"height":156}},"hash":"buckets_07cf4a875d","ext":".jpg","mime":"image/jpeg","size":233.22,"url":"/uploads/buckets_07cf4a875d.jpg","previewUrl":null,"provider":"local","provider_metadata":null,"folderPath":"/","createdAt":"2023-12-18T01:45:07.745Z","updatedAt":"2024-06-04T02:39:23.522Z"}